alexandria/__init__.py
alexandria/__main__.py
alexandria/app.py
alexandria/app_header.py
alexandria/book.py
alexandria/books_view.py
alexandria/footer.py
alexandria/searchbar.py
assets/styles.tcss
alexandria_tui-0.2.0.dist-info/METADATA
alexandria_tui-0.2.0.dist-info/WHEEL
alexandria_tui-0.2.0.dist-info/entry_points.txt
alexandria_tui-0.2.0.dist-info/RECORD
